doc_manager_mcp/__init__.py
doc_manager_mcp/constants.py
doc_manager_mcp/models.py
doc_manager_mcp/server.py
doc_manager_mcp/core/__init__.py
doc_manager_mcp/core/actions.py
doc_manager_mcp/core/api_coverage.py
doc_manager_mcp/core/checksums.py
doc_manager_mcp/core/config.py
doc_manager_mcp/core/conventions.py
doc_manager_mcp/core/errors.py
doc_manager_mcp/core/file_scanner.py
doc_manager_mcp/core/git.py
doc_manager_mcp/core/gitignore.py
doc_manager_mcp/core/markdown_cache.py
doc_manager_mcp/core/paths.py
doc_manager_mcp/core/patterns.py
doc_manager_mcp/core/project.py
doc_manager_mcp/core/resources.py
doc_manager_mcp/core/responses.py
doc_manager_mcp/core/security.py
doc_manager_mcp/core/staleness.py
doc_manager_mcp/indexing/__init__.py
doc_manager_mcp/indexing/link_index.py
doc_manager_mcp/indexing/path_index.py
doc_manager_mcp/indexing/analysis/__init__.py
doc_manager_mcp/indexing/analysis/code_validator.py
doc_manager_mcp/indexing/analysis/semantic_diff.py
doc_manager_mcp/indexing/analysis/tree_sitter.py
doc_manager_mcp/indexing/parsers/__init__.py
doc_manager_mcp/indexing/parsers/markdown.py
doc_manager_mcp/indexing/transforms/__init__.py
doc_manager_mcp/indexing/transforms/links.py
doc_manager_mcp/schemas/__init__.py
doc_manager_mcp/schemas/baselines.py
doc_manager_mcp/schemas/config.py
doc_manager_mcp/schemas/metadata.py
doc_manager_mcp/tools/__init__.py
doc_manager_mcp/tools/_internal/__init__.py
doc_manager_mcp/tools/_internal/baselines.py
doc_manager_mcp/tools/_internal/bootstrap.py
doc_manager_mcp/tools/_internal/changes.py
doc_manager_mcp/tools/_internal/config.py
doc_manager_mcp/tools/_internal/dependencies.py
doc_manager_mcp/tools/_internal/memory.py
doc_manager_mcp/tools/analysis/__init__.py
doc_manager_mcp/tools/analysis/detect_changes.py
doc_manager_mcp/tools/analysis/platform.py
doc_manager_mcp/tools/analysis/quality/__init__.py
doc_manager_mcp/tools/analysis/quality/accuracy.py
doc_manager_mcp/tools/analysis/quality/assessment.py
doc_manager_mcp-1.2.6.dist-info/METADATA
doc_manager_mcp-1.2.6.dist-info/WHEEL
doc_manager_mcp-1.2.6.dist-info/entry_points.txt
doc_manager_mcp-1.2.6.dist-info/licenses/LICENSE
doc_manager_mcp-1.2.6.dist-info/RECORD
