Metadata-Version: 2.4
Name: doc-manager-mcp
Version: 1.2.6
Summary: MCP server for comprehensive documentation lifecycle management
License: MIT
License-File: LICENSE
Classifier: Development Status :: 4 - Beta
Classifier: Intended Audience :: Developers
Classifier: License :: OSI Approved :: MIT License
Classifier: Programming Language :: Python :: 3
Classifier: Programming Language :: Python :: 3.10
Classifier: Programming Language :: Python :: 3.11
Classifier: Programming Language :: Python :: 3.12
Classifier: Programming Language :: Python :: 3.13
Classifier: Topic :: Software Development :: Documentation
Classifier: Topic :: Software Development :: Libraries :: Python Modules
Requires-Python: >=3.10
Requires-Dist: markdown-it-py>=4.0.0
Requires-Dist: mcp>=1.0.0
Requires-Dist: pathspec>=0.12.0
Requires-Dist: pydantic>=2.0.0
Requires-Dist: pyright>=1.1.407
Requires-Dist: pytest-asyncio>=1.3.0
Requires-Dist: pytest-cov>=7.0.0
Requires-Dist: pytest>=9.0.1
Requires-Dist: python-frontmatter>=1.1.0
Requires-Dist: pyyaml>=6.0.0
Requires-Dist: ruff>=0.14.5
Requires-Dist: toml>=0.10.2
Requires-Dist: tree-sitter-language-pack>=0.1.0
Requires-Dist: tree-sitter>=0.21.0
Provides-Extra: dev
Requires-Dist: ruff>=0.8.0; extra == 'dev'
